myscale_telemetry/__init__.py
myscale_telemetry/consumer.py
myscale_telemetry/handler.py
myscale_telemetry/span_data.py
myscale_telemetry/task_manager.py
myscale_telemetry-0.3.2.dist-info/LICENSE
myscale_telemetry-0.3.2.dist-info/METADATA
myscale_telemetry-0.3.2.dist-info/WHEEL
myscale_telemetry-0.3.2.dist-info/top_level.txt
myscale_telemetry-0.3.2.dist-info/RECORD
