Metadata-Version: 2.1
Name: myscale-telemetry
Version: 0.3.2
Summary: Open-source observability for your LLM application.
Home-page: https://github.com/myscale/myscale-telemetry
Author: Xu Jing
Author-email: xuj@myscale.com
Classifier: Programming Language :: Python :: 3
Classifier: License :: OSI Approved :: MIT License
Classifier: Operating System :: OS Independent
Requires-Python: >=3.10
License-File: LICENSE
Requires-Dist: backoff>=2.2.1
Requires-Dist: langchain~=0.3.0
Requires-Dist: langchain-community~=0.3.0
Requires-Dist: clickhouse-connect>=0.7
Requires-Dist: langchain-openai~=0.2.0
Requires-Dist: tiktoken>=0.7.0
